fast_auth/__init__.py
fast_auth/auth/__init__.py
fast_auth/auth/auth.py
fast_auth/auth/crypt.py
fast_auth/database.py
fast_auth/migration.py
fast_auth/models.py
fast_auth/utils.py
fast_auth-0.1.3.dist-info/entry_points.txt
fast_auth-0.1.3.dist-info/WHEEL
fast_auth-0.1.3.dist-info/METADATA
fast_auth-0.1.3.dist-info/RECORD
