Metadata-Version: 2.1
Name: fast-auth
Version: 0.1.3
Summary: Simple implementation of authentication in projects using FastAPI
Home-page: https://github.com/douglasob/fast-auth
Author: Douglas de Oliveira Braga
Author-email: douglasob94@gmail.com
Requires-Python: >=3.9,<4.0
Classifier: Programming Language :: Python :: 3
Classifier: Programming Language :: Python :: 3.10
Classifier: Programming Language :: Python :: 3.9
Requires-Dist: SQLAlchemy (>=1.4.30,<2.0.0)
Requires-Dist: aiosqlite (>=0.17.0,<0.18.0)
Requires-Dist: fastapi (>=0.72.0,<0.73.0)
Requires-Dist: isort (>=5.10.1,<6.0.0)
Requires-Dist: passlib (>=1.7.4,<2.0.0)
Requires-Dist: python-dotenv (>=0.19.2,<0.20.0)
Requires-Dist: python-jose (>=3.3.0,<4.0.0)
Project-URL: Repository, https://github.com/douglasob/fast-auth
